{
  "materials": [
    { "id": "agglomere", "displayName": "Aggloméré", "folder": "0X00X001", "meta": "agglomere.json", "maps": { "basecolor": "basecolor.png", "normal": "normalmap.png", "roughness": "roughnessmap.png", "ao": "AOmap.png" } },
    { "id": "chene", "displayName": "Chêne", "folder": "0X00X002", "meta": "chene.json", "maps": { "basecolor": "basecolor.png", "normal": "normalmap.png", "roughness": "roughnessmap.png", "ao": "AOmap.png" } },
    { "id": "contreplaque_bouleau", "displayName": "Contreplaqué Bouleau", "folder": "0X00X003", "meta": "contreplaque_bouleau.json", "maps": { "basecolor": "basecolor.png", "normal": "normalmap.png", "roughness": "roughnessmap.png", "ao": "AOmap.png" } },
    { "id": "contreplaque_marine_bouleau", "displayName": "Contreplaqué Marine Bouleau", "folder": "0X00X004", "meta": "contreplaque_marine_bouleau.json", "maps": { "basecolor": "basecolor.png", "normal": "normalmap.png", "roughness": "roughnessmap.png", "ao": "AOmap.png" } },
    { "id": "contreplaque_marine_okoume", "displayName": "Contreplaqué Marine Okoumé", "folder": "0X00X005", "meta": "contreplaque_marine_okoume.json", "maps": { "basecolor": "basecolor.png", "normal": "normalmap.png", "roughness": "roughnessmap.png", "ao": "AOmap.png" } },
    { "id": "contreplaque_okoume", "displayName": "Contreplaqué Okoumé", "folder": "0X00X006", "meta": "contreplaque_okoume.json", "maps": { "basecolor": "basecolor.png", "normal": "normalmap.png", "roughness": "roughnessmap.png", "ao": "AOmap.png" } },
    { "id": "contreplaque_peuplier", "displayName": "Contreplaqué Peuplier", "folder": "0X00X007", "meta": "contreplaque_peuplier.json", "maps": { "basecolor": "basecolor.png", "normal": "normalmap.png", "roughness": "roughnessmap.png", "ao": "AOmap.png" } },
    { "id": "douglas", "displayName": "Douglas", "folder": "0X00X008", "meta": "douglas.json", "maps": { "basecolor": "basecolor.png", "normal": "normalmap.png", "roughness": "roughnessmap.png", "ao": "AOmap.png" } },
    { "id": "epicea", "displayName": "Épicéa", "folder": "0X00X009", "meta": "epicea.json", "maps": { "basecolor": "basecolor.png", "normal": "normalmap.png", "roughness": "roughnessmap.png", "ao": "AOmap.png" } },
    { "id": "frene", "displayName": "Frêne", "folder": "0X00X010", "meta": "frene.json", "maps": { "basecolor": "basecolor.png", "normal": "normalmap.png", "roughness": "roughnessmap.png", "ao": "AOmap.png" } },
    { "id": "hetre", "displayName": "Hêtre", "folder": "0X00X011", "meta": "hetre.json", "maps": { "basecolor": "basecolor.png", "normal": "normalmap.png", "roughness": "roughnessmap.png", "ao": "AOmap.png" } },
    { "id": "mdf_hydro", "displayName": "MDF Hydro", "folder": "0X00X012", "meta": "mdf_hydro.json", "maps": { "basecolor": "basecolor.png", "normal": "normalmap.png", "roughness": "roughnessmap.png", "ao": "AOmap.png" } },
    { "id": "mdf_standard", "displayName": "MDF Standard", "folder": "0X00X013", "meta": "mdf_standard.json", "maps": { "basecolor": "basecolor.png", "normal": "normalmap.png", "roughness": "roughnessmap.png", "ao": "AOmap.png" } },
    { "id": "merisier", "displayName": "Merisier", "folder": "0X00X014", "meta": "merisier.json", "maps": { "basecolor": "basecolor.png", "normal": "normalmap.png", "roughness": "roughnessmap.png", "ao": "AOmap.png" } },
    { "id": "noyer", "displayName": "Noyer", "folder": "0X00X015", "meta": "noyer.json", "maps": { "basecolor": "basecolor.png", "normal": "normalmap.png", "roughness": "roughnessmap.png", "ao": "AOmap.png" } },
    { "id": "olivier", "displayName": "Olivier", "folder": "0X00X016", "meta": "olivier.json", "maps": { "basecolor": "basecolor.png", "normal": "normalmap.png", "roughness": "roughnessmap.png", "ao": "AOmap.png" } },
    { "id": "osb_3", "displayName": "OSB 3", "folder": "0X00X017", "meta": "osb_3.json", "maps": { "basecolor": "basecolor.png", "normal": "normalmap.png", "roughness": "roughnessmap.png", "ao": "AOmap.png" } },
    { "id": "pin_sylvestre", "displayName": "Pin sylvestre", "folder": "0X00X018", "meta": "pin_sylvestre.json", "maps": { "basecolor": "basecolor.png", "normal": "normalmap.png", "roughness": "roughnessmap.png", "ao": "AOmap.png" } },
    { "id": "teck", "displayName": "Teck", "folder": "0X00X019", "meta": "teck.json", "maps": { "basecolor": "basecolor.png", "normal": "normalmap.png", "roughness": "roughnessmap.png", "ao": "AOmap.png" } }
  ]
}
